MANIFEST.in
README.rst
setup.py
zdbc/__init__.py
zdbc.egg-info/PKG-INFO
zdbc.egg-info/SOURCES.txt
zdbc.egg-info/dependency_links.txt
zdbc.egg-info/top_level.txt