Metadata-Version: 1.0
Name: zdbc
Version: 0.2.4
Summary: Zscheile DataBase Management
Home-page: UNKNOWN
Author: Erik Kai Alain Zscheile
Author-email: erik.zscheile.ytrizja@gmail.com
License: GPL-3
Platform: UNKNOWN
